{"strategy":{"Saturn5":{"trades":[{"pair":"SOL/USDT","stake_amount":8.1252,"max_stake_amount":8.1252,"amount":0.37,"open_date":"2023-03-18 15:30:00+00:00","close_date":"2023-03-18 16:45:00+00:00","open_rate":21.96,"close_rate":22.28,"fee_open":0.001,"fee_close":0.001,"trade_duration":75,"profit_ratio":0.012544832216963364,"profit_abs":0.1020312,"exit_reason":"trailing_stop_loss","initial_stop_loss_abs":19.77,"initial_stop_loss_ratio":-0.1,"stop_loss_abs":22.28,"stop_loss_ratio":-0.005,"min_rate":21.22,"max_rate":22.39,"is_open":false,"enter_tag":"buy_signal_3","leverage":1.0,"is_short":false,"open_timestamp":1679153400000,"close_timestamp":1679157900000,"orders":[{"amount":0.37,"safe_price":21.96,"ft_order_side":"buy","order_filled_timestamp":1679153400000,"ft_is_entry":true},{"amount":0.37,"safe_price":22.28,"ft_order_side":"sell","order_filled_timestamp":1679157900000,"ft_is_entry":false}]},{"pair":"ETH/USDT","stake_amount":8.118678,"max_stake_amount":8.118678,"amount":0.0046,"open_date":"2023-03-18 22:45:00+00:00","close_date":"2023-03-19 01:45:00+00:00","open_rate":1764.93,"close_rate":1777.23,"fee_open":0.001,"fee_close":0.001,"trade_duration":180,"profit_ratio":0.004957188126664734,"profit_abs":0.04028606,"exit_reason":"trailing_stop_loss","initial_stop_loss_abs":1588.44,"initial_stop_loss_ratio":-0.1,"stop_loss_abs":1777.23,"stop_loss_ratio":-0.005,"min_rate":1751.0,"max_rate":1786.16,"is_open":false,"enter_tag":"buy_signal_3","leverage":1.0,"is_short":false,"open_timestamp":1679179500000,"close_timestamp":1679190300000,"orders":[{"amount":0.0046,"safe_price":1764.93,"ft_order_side":"buy","order_filled_timestamp":1679179500000,"ft_is_entry":true},{"amount":0.0046,"safe_price":1777.23,"ft_order_side":"sell","order_filled_timestamp":1679190300000,"ft_is_entry":false}]},{"pair":"ADA/USDT","stake_amount":8.21752,"max_stake_amount":8.21752,"amount":23.6,"open_date":"2023-03-18 15:30:00+00:00","close_date":"2023-03-19 19:10:00+00:00","open_rate":0.3482,"close_rate":0.3508,"fee_open":0.001,"fee_close":0.001,"trade_duration":1660,"profit_ratio":0.00545405197903762,"profit_abs":0.0448636,"exit_reason":"trailing_stop_loss","initial_stop_loss_abs":0.3134,"initial_stop_loss_ratio":-0.1,"stop_loss_abs":0.3508,"stop_loss_ratio":-0.005,"min_rate":0.335,"max_rate":0.35250000000000004,"is_open":false,"enter_tag":"buy_signal_3","leverage":1.0,"is_short":false,"open_timestamp":1679153400000,"close_timestamp":1679253000000,"orders":[{"amount":23.6,"safe_price":0.3482,"ft_order_side":"buy","order_filled_timestamp":1679153400000,"ft_is_entry":true},{"amount":23.6,"safe_price":0.3508,"ft_order_side":"sell","order_filled_timestamp":1679253000000,"ft_is_entry":false}]},{"pair":"ADA/USDT","stake_amount":8.29281,"max_stake_amount":8.29281,"amount":24.1,"open_date":"2023-03-19 20:40:00+00:00","close_date":"2023-03-19 22:20:00+00:00","open_rate":0.3441,"close_rate":0.3468,"fee_open":0.001,"fee_close":0.001,"trade_duration":100,"profit_ratio":0.005832876800618736,"profit_abs":0.04841931,"exit_reason":"trailing_stop_loss","initial_stop_loss_abs":0.3097,"initial_stop_loss_ratio":-0.1,"stop_loss_abs":0.3468,"stop_loss_ratio":-0.005,"min_rate":0.3438,"max_rate":0.34850000000000003,"is_open":false,"enter_tag":"buy_signal_3","leverage":1.0,"is_short":false,"open_timestamp":1679258400000,"close_timestamp":1679264400000,"orders":[{"amount":24.1,"safe_price":0.3441,"ft_order_side":"buy","order_filled_timestamp":1679258400000,"ft_is_entry":true},{"amount":24.1,"safe_price":0.3468,"ft_order_side":"sell","order_filled_timestamp":1679264400000,"ft_is_entry":false}]},{"pair":"ETH/USDT","stake_amount":8.177558,"max_stake_amount":8.177558,"amount":0.0046,"open_date":"2023-03-19 23:55:00+00:00","close_date":"2023-03-20 08:00:00+00:00","open_rate":1777.73,"close_rate":1792.78,"fee_open":0.001,"fee_close":0.001,"trade_duration":485,"profit_ratio":0.0064509352428802225,"profit_abs":0.05280565,"exit_reason":"trailing_stop_loss","initial_stop_loss_abs":1599.96,"initial_stop_loss_ratio":-0.1,"stop_loss_abs":1792.78,"stop_loss_ratio":-0.005,"min_rate":1736.57,"max_rate":1801.78,"is_open":false,"enter_tag":"buy_signal_3","leverage":1.0,"is_short":false,"open_timestamp":1679270100000,"close_timestamp":1679299200000,"orders":[{"amount":0.0046,"safe_price":1777.73,"ft_order_side":"buy","order_filled_timestamp":1679270100000,"ft_is_entry":true},{"amount":0.0046,"safe_price":1792.78,"ft_order_side":"sell","order_filled_timestamp":1679299200000,"ft_is_entry":false}]},{"pair":"ETH/USDT","stake_amount":8.271624,"max_stake_amount":8.271624,"amount":0.0047,"open_date":"2023-03-20 13:40:00+00:00","close_date":"2023-03-21 12:40:00+00:00","open_rate":1759.92,"close_rate":1780.09,"fee_open":0.001,"fee_close":0.001,"trade_duration":1380,"profit_ratio":0.009439847257668764,"profit_abs":0.07816095,"exit_reason":"trailing_stop_loss","initial_stop_loss_abs":1583.93,"initial_stop_loss_ratio":-0.1,"stop_loss_abs":1780.09,"stop_loss_ratio":-0.005,"min_rate":1717.01,"max_rate":1789.03,"is_open":false,"enter_tag":"buy_signal_3","leverage":1.0,"is_short":false,"open_timestamp":1679319600000,"close_timestamp":1679402400000,"orders":[{"amount":0.0047,"safe_price":1759.92,"ft_order_side":"buy","order_filled_timestamp":1679319600000,"ft_is_entry":true},{"amount":0.0047,"safe_price":1780.09,"ft_order_side":"sell","order_filled_timestamp":1679402400000,"ft_is_entry":false}]},{"pair":"ADA/USDT","stake_amount":8.32238,"max_stake_amount":8.32238,"amount":24.2,"open_date":"2023-03-19 23:55:00+00:00","close_date":"2023-03-21 13:25:00+00:00","open_rate":0.34390000000000004,"close_rate":0.3501,"fee_open":0.001,"fee_close":0.001,"trade_duration":2250,"profit_ratio":0.015994473685662983,"profit_abs":0.1332452,"exit_reason":"trailing_stop_loss","initial_stop_loss_abs":0.3096,"initial_stop_loss_ratio":-0.1,"stop_loss_abs":0.3501,"stop_loss_ratio":-0.005,"min_rate":0.3291,"max_rate":0.3518,"is_open":false,"enter_tag":"buy_signal_3","leverage":1.0,"is_short":false,"open_timestamp":1679270100000,"close_timestamp":1679405100000,"orders":[{"amount":24.2,"safe_price":0.34390000000000004,"ft_order_side":"buy","order_filled_timestamp":1679270100000,"ft_is_entry":true},{"amount":24.2,"safe_price":0.3501,"ft_order_side":"sell","order_filled_timestamp":1679405100000,"ft_is_entry":false}]},{"pair":"DOGE/USDT","stake_amount":8.21448,"max_stake_amount":8.21448,"amount":108.0,"open_date":"2023-03-18 15:30:00+00:00","close_date":"2023-03-21 17:10:00+00:00","open_rate":0.07606,"close_rate":0.07692,"fee_open":0.001,"fee_close":0.001,"trade_duration":4420,"profit_ratio":0.00928626987001954,"profit_abs":0.07635816,"exit_reason":"trailing_stop_loss","initial_stop_loss_abs":0.06846,"initial_stop_loss_ratio":-0.1,"stop_loss_abs":0.07692,"stop_loss_ratio":-0.005,"min_rate":0.07031000000000001,"max_rate":0.07730000000000001,"is_open":false,"enter_tag":"buy_signal_3","leverage":1.0,"is_short":false,"open_timestamp":1679153400000,"close_timestamp":1679418600000,"orders":[{"amount":108.0,"safe_price":0.07606,"ft_order_side":"buy","order_filled_timestamp":1679153400000,"ft_is_entry":true},{"amount":108.0,"safe_price":0.07692,"ft_order_side":"sell","order_filled_timestamp":1679418600000,"ft_is_entry":false}]},{"pair":"SOL/USDT","stake_amount":8.2547,"max_stake_amount":8.2547,"amount":0.37,"open_date":"2023-03-21 21:15:00+00:00","close_date":"2023-03-21 21:35:00+00:00","open_rate":22.31,"close_rate":22.48,"fee_open":0.001,"fee_close":0.001,"trade_duration":20,"profit_ratio":0.0056066748133086096,"profit_abs":0.0463277,"exit_reason":"trailing_stop_loss","initial_stop_loss_abs":20.08,"initial_stop_loss_ratio":-0.1,"stop_loss_abs":22.48,"stop_loss_ratio":-0.005,"min_rate":22.25,"max_rate":22.59,"is_open":false,"enter_tag":"buy_signal_3","leverage":1.0,"is_short":false,"open_timestamp":1679433300000,"close_timestamp":1679434500000,"orders":[{"amount":0.37,"safe_price":22.31,"ft_order_side":"buy","order_filled_timestamp":1679433300000,"ft_is_entry":true},{"amount":0.37,"safe_price":22.48,"ft_order_side":"sell","order_filled_timestamp":1679434500000,"ft_is_entry":false}]},{"pair":"BTC/USDT","stake_amount":8.418783,"max_stake_amount":8.418783,"amount":0.0003,"open_date":"2023-03-22 01:30:00+00:00","close_date":"2023-03-22 14:35:00+00:00","open_rate":28062.61,"close_rate":28347.55,"fee_open":0.001,"fee_close":0.001,"trade_duration":785,"profit_ratio":0.00813543472262672,"profit_abs":0.06855895,"exit_reason":"trailing_stop_loss","initial_stop_loss_abs":25256.35,"initial_stop_loss_ratio":-0.1,"stop_loss_abs":28347.55,"stop_loss_ratio":-0.005,"min_rate":27995.0,"max_rate":28490.0,"is_open":false,"enter_tag":"buy_signal_1","leverage":1.0,"is_short":false,"open_timestamp":1679448600000,"close_timestamp":1679495700000,"orders":[{"amount":0.0003,"safe_price":28062.61,"ft_order_side":"buy","order_filled_timestamp":1679448600000,"ft_is_entry":true},{"amount":0.0003,"safe_price":28347.55,"ft_order_side":"sell","order_filled_timestamp":1679495700000,"ft_is_entry":false}]},{"pair":"SOL/USDT","stake_amount":8.4208,"max_stake_amount":8.4208,"amount":0.38,"open_date":"2023-03-22 18:40:00+00:00","close_date":"2023-03-22 18:40:00+00:00","open_rate":22.16,"close_rate":22.2708,"fee_open":0.001,"fee_close":0.001,"trade_duration":0,"profit_ratio":0.002992008466547703,"profit_abs":0.0252203,"exit_reason":"trailing_stop_loss","initial_stop_loss_abs":19.95,"initial_stop_loss_ratio":-0.1,"stop_loss_abs":22.32,"stop_loss_ratio":-0.005,"min_rate":22.14,"max_rate":22.43,"is_open":false,"enter_tag":"buy_signal_3","leverage":1.0,"is_short":false,"open_timestamp":1679510400000,"close_timestamp":1679510400000,"orders":[{"amount":0.38,"safe_price":22.16,"ft_order_side":"buy","order_filled_timestamp":1679510400000,"ft_is_entry":true},{"amount":0.38,"safe_price":22.2708,"ft_order_side":"sell","order_filled_timestamp":1679510400000,"ft_is_entry":false}]},{"pair":"BTC/USDT","stake_amount":8.383977,"max_stake_amount":8.383977,"amount":0.0003,"open_date":"2023-03-22 18:40:00+00:00","close_date":"2023-03-22 18:45:00+00:00","open_rate":27946.59,"close_rate":28340.12,"fee_open":0.001,"fee_close":0.001,"trade_duration":5,"profit_ratio":0.012055366812423042,"profit_abs":0.10117299,"exit_reason":"trailing_stop_loss","initial_stop_loss_abs":25151.94,"initial_stop_loss_ratio":-0.1,"stop_loss_abs":28340.12,"stop_loss_ratio":-0.005,"min_rate":27946.58,"max_rate":28482.53,"is_open":false,"enter_tag":"buy_signal_3","leverage":1.0,"is_short":false,"open_timestamp":1679510400000,"close_timestamp":1679510700000,"orders":[{"amount":0.0003,"safe_price":27946.59,"ft_order_side":"buy","order_filled_timestamp":1679510400000,"ft_is_entry":true},{"amount":0.0003,"safe_price":28340.12,"ft_order_side":"sell","order_filled_timestamp":1679510700000,"ft_is_entry":false}]},{"pair":"DOGE/USDT","stake_amount":8.47726,"max_stake_amount":8.47726,"amount":113.0,"open_date":"2023-03-22 18:40:00+00:00","close_date":"2023-03-22 18:45:00+00:00","open_rate":0.07502,"close_rate":0.07622,"fee_open":0.001,"fee_close":0.001,"trade_duration":5,"profit_ratio":0.013965772963373603,"profit_abs":0.11850988,"exit_reason":"trailing_stop_loss","initial_stop_loss_abs":0.06752,"initial_stop_loss_ratio":-0.1,"stop_loss_abs":0.07622,"stop_loss_ratio":-0.005,"min_rate":0.07502,"max_rate":0.0766,"is_open":false,"enter_tag":"buy_signal_3","leverage":1.0,"is_short":false,"open_timestamp":1679510400000,"close_timestamp":1679510700000,"orders":[{"amount":113.0,"safe_price":0.07502,"ft_order_side":"buy","order_filled_timestamp":1679510400000,"ft_is_entry":true},{"amount":113.0,"safe_price":0.07622,"ft_order_side":"sell","order_filled_timestamp":1679510700000,"ft_is_entry":false}]},{"pair":"ETH/USDT","stake_amount":8.485281,"max_stake_amount":8.485281,"amount":0.0049,"open_date":"2023-03-23 05:00:00+00:00","close_date":"2023-03-23 07:20:00+00:00","open_rate":1731.69,"close_rate":1744.81,"fee_open":0.001,"fee_close":0.001,"trade_duration":140,"profit_ratio":0.005563274104410221,"profit_abs":0.04725315,"exit_reason":"trailing_stop_loss","initial_stop_loss_abs":1558.53,"initial_stop_loss_ratio":-0.1,"stop_loss_abs":1744.81,"stop_loss_ratio":-0.005,"min_rate":1730.44,"max_rate":1753.57,"is_open":false,"enter_tag":"buy_signal_3","leverage":1.0,"is_short":false,"open_timestamp":1679547600000,"close_timestamp":1679556000000,"orders":[{"amount":0.0049,"safe_price":1731.69,"ft_order_side":"buy","order_filled_timestamp":1679547600000,"ft_is_entry":true},{"amount":0.0049,"safe_price":1744.81,"ft_order_side":"sell","order_filled_timestamp":1679556000000,"ft_is_entry":false}]},{"pair":"DOGE/USDT","stake_amount":8.56688,"max_stake_amount":8.56688,"amount":112.0,"open_date":"2023-03-23 21:20:00+00:00","close_date":"2023-03-23 23:55:00+00:00","open_rate":0.07649,"close_rate":0.07726,"fee_open":0.001,"fee_close":0.001,"trade_duration":155,"profit_ratio":0.008048560146873652,"profit_abs":0.06902,"exit_reason":"trailing_stop_loss","initial_stop_loss_abs":0.06885,"initial_stop_loss_ratio":-0.1,"stop_loss_abs":0.07726,"stop_loss_ratio":-0.005,"min_rate":0.07645,"max_rate":0.07764,"is_open":false,"enter_tag":"buy_signal_3","leverage":1.0,"is_short":false,"open_timestamp":1679606400000,"close_timestamp":1679615700000,"orders":[{"amount":112.0,"safe_price":0.07649,"ft_order_side":"buy","order_filled_timestamp":1679606400000,"ft_is_entry":true},{"amount":112.0,"safe_price":0.07726,"ft_order_side":"sell","order_filled_timestamp":1679615700000,"ft_is_entry":false}]},{"pair":"ADA/USDT","stake_amount":8.59096,"max_stake_amount":8.59096,"amount":23.2,"open_date":"2023-03-24 01:40:00+00:00","close_date":"2023-03-29 02:25:00+00:00","open_rate":0.3703,"close_rate":0.3743,"fee_open":0.001,"fee_close":0.001,"trade_duration":7245,"profit_ratio":0.008782467869694442,"profit_abs":0.07552528,"exit_reason":"trailing_stop_loss","initial_stop_loss_abs":0.3333,"initial_stop_loss_ratio":-0.1,"stop_loss_abs":0.3743,"stop_loss_ratio":-0.005,"min_rate":0.3366,"max_rate":0.37610000000000005,"is_open":false,"enter_tag":"buy_signal_1","leverage":1.0,"is_short":false,"open_timestamp":1679622000000,"close_timestamp":1680056700000,"orders":[{"amount":23.2,"safe_price":0.3703,"ft_order_side":"buy","order_filled_timestamp":1679622000000,"ft_is_entry":true},{"amount":23.2,"safe_price":0.3743,"ft_order_side":"sell","order_filled_timestamp":1680056700000,"ft_is_entry":false}]},{"pair":"BTC/USDT","stake_amount":8.450844,"max_stake_amount":8.450844,"amount":0.0003,"open_date":"2023-03-24 04:45:00+00:00","close_date":"2023-03-29 08:30:00+00:00","open_rate":28169.48,"close_rate":28479.72,"fee_open":0.001,"fee_close":0.001,"trade_duration":7425,"profit_ratio":0.008993331170382361,"profit_abs":0.07607724,"exit_reason":"trailing_stop_loss","initial_stop_loss_abs":25352.54,"initial_stop_loss_ratio":-0.1,"stop_loss_abs":28479.72,"stop_loss_ratio":-0.005,"min_rate":26508.14,"max_rate":28622.83,"is_open":false,"enter_tag":"buy_signal_3","leverage":1.0,"is_short":false,"open_timestamp":1679633100000,"close_timestamp":1680078600000,"orders":[{"amount":0.0003,"safe_price":28169.48,"ft_order_side":"buy","order_filled_timestamp":1679633100000,"ft_is_entry":true},{"amount":0.0003,"safe_price":28479.72,"ft_order_side":"sell","order_filled_timestamp":1680078600000,"ft_is_entry":false}]},{"pair":"ETH/USDT","stake_amount":8.48115,"max_stake_amount":8.48115,"amount":0.0047,"open_date":"2023-03-24 05:00:00+00:00","close_date":"2023-03-29 08:40:00+00:00","open_rate":1804.5,"close_rate":1818.86,"fee_open":0.001,"fee_close":0.001,"trade_duration":7420,"profit_ratio":0.005943981441408088,"profit_abs":0.05046221,"exit_reason":"trailing_stop_loss","initial_stop_loss_abs":1624.05,"initial_stop_loss_ratio":-0.1,"stop_loss_abs":1818.86,"stop_loss_ratio":-0.005,"min_rate":1686.13,"max_rate":1827.99,"is_open":false,"enter_tag":"buy_signal_3","leverage":1.0,"is_short":false,"open_timestamp":1679634000000,"close_timestamp":1680079200000,"orders":[{"amount":0.0047,"safe_price":1804.5,"ft_order_side":"buy","order_filled_timestamp":1679634000000,"ft_is_entry":true},{"amount":0.0047,"safe_price":1818.86,"ft_order_side":"sell","order_filled_timestamp":1680079200000,"ft_is_entry":false}]},{"pair":"BTC/USDT","stake_amount":8.466453,"max_stake_amount":8.466453,"amount":0.0003,"open_date":"2023-03-29 22:05:00+00:00","close_date":"2023-03-30 02:15:00+00:00","open_rate":28221.51,"close_rate":28457.0,"fee_open":0.001,"fee_close":0.001,"trade_duration":250,"profit_ratio":0.006329670777108211,"profit_abs":0.05364345,"exit_reason":"trailing_stop_loss","initial_stop_loss_abs":25399.36,"initial_stop_loss_ratio":-0.1,"stop_loss_abs":28457.0,"stop_loss_ratio":-0.005,"min_rate":28218.28,"max_rate":28600.0,"is_open":false,"enter_tag":"buy_signal_3","leverage":1.0,"is_short":false,"open_timestamp":1680127500000,"close_timestamp":1680142500000,"orders":[{"amount":0.0003,"safe_price":28221.51,"ft_order_side":"buy","order_filled_timestamp":1680127500000,"ft_is_entry":true},{"amount":0.0003,"safe_price":28457.0,"ft_order_side":"sell","order_filled_timestamp":1680142500000,"ft_is_entry":false}]},{"pair":"ETH/USDT","stake_amount":8.562768,"max_stake_amount":8.562768,"amount":0.0048,"open_date":"2023-03-29 22:05:00+00:00","close_date":"2023-03-30 02:15:00+00:00","open_rate":1783.91,"close_rate":1798.41,"fee_open":0.001,"fee_close":0.001,"trade_duration":250,"profit_ratio":0.006113970096177719,"profit_abs":0.05240486,"exit_reason":"trailing_stop_loss","initial_stop_loss_abs":1605.52,"initial_stop_loss_ratio":-0.1,"stop_loss_abs":1798.41,"stop_loss_ratio":-0.005,"min_rate":1776.43,"max_rate":1807.44,"is_open":false,"enter_tag":"buy_signal_3","leverage":1.0,"is_short":false,"open_timestamp":1680127500000,"close_timestamp":1680142500000,"orders":[{"amount":0.0048,"safe_price":1783.91,"ft_order_side":"buy","order_filled_timestamp":1680127500000,"ft_is_entry":true},{"amount":0.0048,"safe_price":1798.41,"ft_order_side":"sell","order_filled_timestamp":1680142500000,"ft_is_entry":false}]},{"pair":"ADA/USDT","stake_amount":8.6487,"max_stake_amount":8.6487,"amount":22.7,"open_date":"2023-03-29 22:05:00+00:00","close_date":"2023-03-30 02:35:00+00:00","open_rate":0.381,"close_rate":0.3847,"fee_open":0.001,"fee_close":0.001,"trade_duration":270,"profit_ratio":0.007693880922227379,"profit_abs":0.06660861,"exit_reason":"trailing_stop_loss","initial_stop_loss_abs":0.343,"initial_stop_loss_ratio":-0.1,"stop_loss_abs":0.3847,"stop_loss_ratio":-0.005,"min_rate":0.3748,"max_rate":0.3866,"is_open":false,"enter_tag":"buy_signal_3","leverage":1.0,"is_short":false,"open_timestamp":1680127500000,"close_timestamp":1680143700000,"orders":[{"amount":22.7,"safe_price":0.381,"ft_order_side":"buy","order_filled_timestamp":1680127500000,"ft_is_entry":true},{"amount":22.7,"safe_price":0.3847,"ft_order_side":"sell","order_filled_timestamp":1680143700000,"ft_is_entry":false}]},{"pair":"ADA/USDT","stake_amount":8.70276,"max_stake_amount":8.70276,"amount":22.8,"open_date":"2023-03-30 03:50:00+00:00","close_date":"2023-03-31 08:00:00+00:00","open_rate":0.38170000000000004,"close_rate":0.3852,"fee_open":0.001,"fee_close":0.001,"trade_duration":1690,"profit_ratio":0.007153182159731804,"profit_abs":0.06231468,"exit_reason":"trailing_stop_loss","initial_stop_loss_abs":0.3436,"initial_stop_loss_ratio":-0.1,"stop_loss_abs":0.3852,"stop_loss_ratio":-0.005,"min_rate":0.36970000000000003,"max_rate":0.3871,"is_open":false,"enter_tag":"buy_signal_1","leverage":1.0,"is_short":false,"open_timestamp":1680148200000,"close_timestamp":1680249600000,"orders":[{"amount":22.8,"safe_price":0.38170000000000004,"ft_order_side":"buy","order_filled_timestamp":1680148200000,"ft_is_entry":true},{"amount":22.8,"safe_price":0.3852,"ft_order_side":"sell","order_filled_timestamp":1680249600000,"ft_is_entry":false}]},{"pair":"ETH/USDT","stake_amount":8.632848,"max_stake_amount":8.632848,"amount":0.0048,"open_date":"2023-03-30 13:55:00+00:00","close_date":"2023-03-31 13:30:00+00:00","open_rate":1798.51,"close_rate":1825.83,"fee_open":0.001,"fee_close":0.001,"trade_duration":1415,"profit_ratio":0.013161999893377532,"profit_abs":0.11373917,"exit_reason":"trailing_stop_loss","initial_stop_loss_abs":1618.66,"initial_stop_loss_ratio":-0.1,"stop_loss_abs":1825.83,"stop_loss_ratio":-0.005,"min_rate":1763.0,"max_rate":1835.0,"is_open":false,"enter_tag":"buy_signal_3","leverage":1.0,"is_short":false,"open_timestamp":1680184500000,"close_timestamp":1680269400000,"orders":[{"amount":0.0048,"safe_price":1798.51,"ft_order_side":"buy","order_filled_timestamp":1680184500000,"ft_is_entry":true},{"amount":0.0048,"safe_price":1825.83,"ft_order_side":"sell","order_filled_timestamp":1680269400000,"ft_is_entry":false}]},{"pair":"ETH/USDT","stake_amount":8.72496,"max_stake_amount":8.72496,"amount":0.0048,"open_date":"2023-03-31 21:00:00+00:00","close_date":"2023-04-01 02:00:00+00:00","open_rate":1817.7,"close_rate":1833.62,"fee_open":0.001,"fee_close":0.001,"trade_duration":300,"profit_ratio":0.006742819356286926,"profit_abs":0.05888966,"exit_reason":"trailing_stop_loss","initial_stop_loss_abs":1635.93,"initial_stop_loss_ratio":-0.1,"stop_loss_abs":1833.62,"stop_loss_ratio":-0.005,"min_rate":1815.2,"max_rate":1842.83,"is_open":false,"enter_tag":"buy_signal_3","leverage":1.0,"is_short":false,"open_timestamp":1680296400000,"close_timestamp":1680314400000,"orders":[{"amount":0.0048,"safe_price":1817.7,"ft_order_side":"buy","order_filled_timestamp":1680296400000,"ft_is_entry":true},{"amount":0.0048,"safe_price":1833.62,"ft_order_side":"sell","order_filled_timestamp":1680314400000,"ft_is_entry":false}]},{"pair":"ADA/USDT","stake_amount":8.78625,"max_stake_amount":8.78625,"amount":22.5,"open_date":"2023-04-01 11:15:00+00:00","close_date":"2023-04-01 19:15:00+00:00","open_rate":0.3905,"close_rate":0.3939,"fee_open":0.001,"fee_close":0.001,"trade_duration":480,"profit_ratio":0.006691387997405923,"profit_abs":0.058851,"exit_reason":"trailing_stop_loss","initial_stop_loss_abs":0.3515,"initial_stop_loss_ratio":-0.1,"stop_loss_abs":0.3939,"stop_loss_ratio":-0.005,"min_rate":0.388,"max_rate":0.39580000000000004,"is_open":false,"enter_tag":"buy_signal_3","leverage":1.0,"is_short":false,"open_timestamp":1680347700000,"close_timestamp":1680376500000,"orders":[{"amount":22.5,"safe_price":0.3905,"ft_order_side":"buy","order_filled_timestamp":1680347700000,"ft_is_entry":true},{"amount":22.5,"safe_price":0.3939,"ft_order_side":"sell","order_filled_timestamp":1680376500000,"ft_is_entry":false}]},{"pair":"SOL/USDT","stake_amount":8.61,"max_stake_amount":8.61,"amount":0.41,"open_date":"2023-04-02 00:40:00+00:00","close_date":"2023-04-02 07:25:00+00:00","open_rate":21.0,"close_rate":21.2,"fee_open":0.001,"fee_close":0.001,"trade_duration":405,"profit_ratio":0.007506778935350364,"profit_abs":0.064698,"exit_reason":"trailing_stop_loss","initial_stop_loss_abs":18.91,"initial_stop_loss_ratio":-0.1,"stop_loss_abs":21.2,"stop_loss_ratio":-0.005,"min_rate":20.88,"max_rate":21.3,"is_open":false,"enter_tag":"buy_signal_3","leverage":1.0,"is_short":false,"open_timestamp":1680396000000,"close_timestamp":1680420300000,"orders":[{"amount":0.41,"safe_price":21.0,"ft_order_side":"buy","order_filled_timestamp":1680396000000,"ft_is_entry":true},{"amount":0.41,"safe_price":21.2,"ft_order_side":"sell","order_filled_timestamp":1680420300000,"ft_is_entry":false}]},{"pair":"DOGE/USDT","stake_amount":8.83285,"max_stake_amount":8.83285,"amount":107.0,"open_date":"2023-04-02 08:50:00+00:00","close_date":"2023-04-03 17:35:00+00:00","open_rate":0.08255000000000001,"close_rate":0.08458,"fee_open":0.001,"fee_close":0.001,"trade_duration":1965,"profit_ratio":0.022544021696050767,"profit_abs":0.19932709,"exit_reason":"trailing_stop_loss","initial_stop_loss_abs":0.0743,"initial_stop_loss_ratio":-0.1,"stop_loss_abs":0.08458,"stop_loss_ratio":-0.005,"min_rate":0.076,"max_rate":0.085,"is_open":false,"enter_tag":"buy_signal_3","leverage":1.0,"is_short":false,"open_timestamp":1680425400000,"close_timestamp":1680543300000,"orders":[{"amount":107.0,"safe_price":0.08255000000000001,"ft_order_side":"buy","order_filled_timestamp":1680425400000,"ft_is_entry":true},{"amount":107.0,"safe_price":0.08458,"ft_order_side":"sell","order_filled_timestamp":1680543300000,"ft_is_entry":false}]},{"pair":"LTC/USDT","stake_amount":8.87259,"max_stake_amount":8.87259,"amount":0.097,"open_date":"2023-04-03 18:10:00+00:00","close_date":"2023-04-03 18:30:00+00:00","open_rate":91.47,"close_rate":92.25,"fee_open":0.001,"fee_close":0.001,"trade_duration":20,"profit_ratio":0.006512346295881881,"profit_abs":0.05783916,"exit_reason":"trailing_stop_loss","initial_stop_loss_abs":82.33,"initial_stop_loss_ratio":-0.1,"stop_loss_abs":92.25,"stop_loss_ratio":-0.005,"min_rate":91.35,"max_rate":92.71,"is_open":false,"enter_tag":"buy_signal_3","leverage":1.0,"is_short":false,"open_timestamp":1680545400000,"close_timestamp":1680546600000,"orders":[{"amount":0.097,"safe_price":91.47,"ft_order_side":"buy","order_filled_timestamp":1680545400000,"ft_is_entry":true},{"amount":0.097,"safe_price":92.25,"ft_order_side":"sell","order_filled_timestamp":1680546600000,"ft_is_entry":false}]},{"pair":"XRP/USDT","stake_amount":8.901,"max_stake_amount":8.901,"amount":18.0,"open_date":"2023-04-03 20:15:00+00:00","close_date":"2023-04-03 22:15:00+00:00","open_rate":0.49450000000000005,"close_rate":0.4982,"fee_open":0.001,"fee_close":0.001,"trade_duration":120,"profit_ratio":0.005469353699889594,"profit_abs":0.0487314,"exit_reason":"trailing_stop_loss","initial_stop_loss_abs":0.4451,"initial_stop_loss_ratio":-0.1,"stop_loss_abs":0.4982,"stop_loss_ratio":-0.005,"min_rate":0.481,"max_rate":0.5007,"is_open":false,"enter_tag":"buy_signal_3","leverage":1.0,"is_short":false,"open_timestamp":1680552900000,"close_timestamp":1680560100000,"orders":[{"amount":18.0,"safe_price":0.49450000000000005,"ft_order_side":"buy","order_filled_timestamp":1680552900000,"ft_is_entry":true},{"amount":18.0,"safe_price":0.4982,"ft_order_side":"sell","order_filled_timestamp":1680560100000,"ft_is_entry":false}]},{"pair":"ETH/USDT","stake_amount":8.733984,"max_stake_amount":8.733984,"amount":0.0048,"open_date":"2023-04-01 14:20:00+00:00","close_date":"2023-04-04 11:05:00+00:00","open_rate":1819.58,"close_rate":1865.63,"fee_open":0.001,"fee_close":0.001,"trade_duration":4125,"profit_ratio":0.023259470381196273,"profit_abs":0.20335099,"exit_reason":"trailing_stop_loss","initial_stop_loss_abs":1637.63,"initial_stop_loss_ratio":-0.1,"stop_loss_abs":1865.63,"stop_loss_ratio":-0.005,"min_rate":1762.77,"max_rate":1875.0,"is_open":false,"enter_tag":"buy_signal_3","leverage":1.0,"is_short":false,"open_timestamp":1680358800000,"close_timestamp":1680606300000,"orders":[{"amount":0.0048,"safe_price":1819.58,"ft_order_side":"buy","order_filled_timestamp":1680358800000,"ft_is_entry":true},{"amount":0.0048,"safe_price":1865.63,"ft_order_side":"sell","order_filled_timestamp":1680606300000,"ft_is_entry":false}]},{"pair":"XRP/USDT","stake_amount":8.937,"max_stake_amount":8.937,"amount":18.0,"open_date":"2023-04-03 23:50:00+00:00","close_date":"2023-04-04 13:15:00+00:00","open_rate":0.4965,"close_rate":0.5002,"fee_open":0.001,"fee_close":0.001,"trade_duration":805,"profit_ratio":0.005439273717219336,"profit_abs":0.0486594,"exit_reason":"trailing_stop_loss","initial_stop_loss_abs":0.4469,"initial_stop_loss_ratio":-0.1,"stop_loss_abs":0.5002,"stop_loss_ratio":-0.005,"min_rate":0.48710000000000003,"max_rate":0.5027,"is_open":false,"enter_tag":"buy_signal_3","leverage":1.0,"is_short":false,"open_timestamp":1680565800000,"close_timestamp":1680614100000,"orders":[{"amount":18.0,"safe_price":0.4965,"ft_order_side":"buy","order_filled_timestamp":1680565800000,"ft_is_entry":true},{"amount":18.0,"safe_price":0.5002,"ft_order_side":"sell","order_filled_timestamp":1680614100000,"ft_is_entry":false}]},{"pair":"DOGE/USDT","stake_amount":8.94288,"max_stake_amount":8.94288,"amount":93.0,"open_date":"2023-04-04 15:00:00+00:00","close_date":"2023-04-04 15:45:00+00:00","open_rate":0.09616000000000001,"close_rate":0.09692,"fee_open":0.001,"fee_close":0.001,"trade_duration":45,"profit_ratio":0.005889700981215123,"profit_abs":0.05272356,"exit_reason":"trailing_stop_loss","initial_stop_loss_abs":0.08655,"initial_stop_loss_ratio":-0.1,"stop_loss_abs":0.09692,"stop_loss_ratio":-0.005,"min_rate":0.09534000000000001,"max_rate":0.0974,"is_open":false,"enter_tag":"buy_signal_3","leverage":1.0,"is_short":false,"open_timestamp":1680620400000,"close_timestamp":1680623100000,"orders":[{"amount":93.0,"safe_price":0.09616000000000001,"ft_order_side":"buy","order_filled_timestamp":1680620400000,"ft_is_entry":true},{"amount":93.0,"safe_price":0.09692,"ft_order_side":"sell","order_filled_timestamp":1680623100000,"ft_is_entry":false}]},{"pair":"DOGE/USDT","stake_amount":8.98605,"max_stake_amount":8.98605,"amount":95.0,"open_date":"2023-04-04 23:20:00+00:00","close_date":"2023-04-05 00:55:00+00:00","open_rate":0.09459000000000001,"close_rate":0.09552,"fee_open":0.001,"fee_close":0.001,"trade_duration":95,"profit_ratio":0.007814259955078224,"profit_abs":0.07028955,"exit_reason":"trailing_stop_loss","initial_stop_loss_abs":0.08514,"initial_stop_loss_ratio":-0.1,"stop_loss_abs":0.09552,"stop_loss_ratio":-0.005,"min_rate":0.09272000000000001,"max_rate":0.09599,"is_open":false,"enter_tag":"buy_signal_3","leverage":1.0,"is_short":false,"open_timestamp":1680650400000,"close_timestamp":1680656100000,"orders":[{"amount":95.0,"safe_price":0.09459000000000001,"ft_order_side":"buy","order_filled_timestamp":1680650400000,"ft_is_entry":true},{"amount":95.0,"safe_price":0.09552,"ft_order_side":"sell","order_filled_timestamp":1680656100000,"ft_is_entry":false}]},{"pair":"TRX/USDT","stake_amount":9.035424,"max_stake_amount":9.035424,"amount":137.4,"open_date":"2023-04-04 19:45:00+00:00","close_date":"2023-04-05 08:40:00+00:00","open_rate":0.06576,"close_rate":0.06628,"fee_open":0.001,"fee_close":0.001,"trade_duration":775,"profit_ratio":0.0058937408529414394,"profit_abs":0.0533057,"exit_reason":"trailing_stop_loss","initial_stop_loss_abs":0.05919,"initial_stop_loss_ratio":-0.1,"stop_loss_abs":0.06628,"stop_loss_ratio":-0.005,"min_rate":0.06555000000000001,"max_rate":0.06661,"is_open":false,"enter_tag":"buy_signal_3","leverage":1.0,"is_short":false,"open_timestamp":1680637500000,"close_timestamp":1680684000000,"orders":[{"amount":137.4,"safe_price":0.06576,"ft_order_side":"buy","order_filled_timestamp":1680637500000,"ft_is_entry":true},{"amount":137.4,"safe_price":0.06628,"ft_order_side":"sell","order_filled_timestamp":1680684000000,"ft_is_entry":false}]},{"pair":"BTC/USDT","stake_amount":8.553627,"max_stake_amount":8.553627,"amount":0.0003,"open_date":"2023-03-30 13:55:00+00:00","close_date":"2023-04-10 16:50:00+00:00","open_rate":28512.09,"close_rate":28855.0,"fee_open":0.001,"fee_close":0.001,"trade_duration":16015,"profit_ratio":0.010004795942971644,"profit_abs":0.08566287,"exit_reason":"trailing_stop_loss","initial_stop_loss_abs":25660.89,"initial_stop_loss_ratio":-0.1,"stop_loss_abs":28855.0,"stop_loss_ratio":-0.005,"min_rate":27200.24,"max_rate":29000.0,"is_open":false,"enter_tag":"buy_signal_3","leverage":1.0,"is_short":false,"open_timestamp":1680184500000,"close_timestamp":1681145400000,"orders":[{"amount":0.0003,"safe_price":28512.09,"ft_order_side":"buy","order_filled_timestamp":1680184500000,"ft_is_entry":true},{"amount":0.0003,"safe_price":28855.0,"ft_order_side":"sell","order_filled_timestamp":1681145400000,"ft_is_entry":false}]},{"pair":"TRX/USDT","stake_amount":9.07488,"max_stake_amount":9.07488,"amount":137.0,"open_date":"2023-04-05 08:45:00+00:00","close_date":"2023-04-10 22:00:00+00:00","open_rate":0.06624000000000001,"close_rate":0.06706,"fee_open":0.001,"fee_close":0.001,"trade_duration":7995,"profit_ratio":0.010356491334752202,"profit_abs":0.0940779,"exit_reason":"trailing_stop_loss","initial_stop_loss_abs":0.05962,"initial_stop_loss_ratio":-0.1,"stop_loss_abs":0.06706,"stop_loss_ratio":-0.005,"min_rate":0.06534000000000001,"max_rate":0.06739,"is_open":false,"enter_tag":"buy_signal_3","leverage":1.0,"is_short":false,"open_timestamp":1680684300000,"close_timestamp":1681164000000,"orders":[{"amount":137.0,"safe_price":0.06624000000000001,"ft_order_side":"buy","order_filled_timestamp":1680684300000,"ft_is_entry":true},{"amount":137.0,"safe_price":0.06706,"ft_order_side":"sell","order_filled_timestamp":1681164000000,"ft_is_entry":false}]},{"pair":"LINK/USDT","stake_amount":9.06,"max_stake_amount":9.06,"amount":1.25,"open_date":"2023-04-10 21:30:00+00:00","close_date":"2023-04-10 22:00:00+00:00","open_rate":7.248,"close_rate":7.304,"fee_open":0.001,"fee_close":0.001,"trade_duration":30,"profit_ratio":0.005712830216141474,"profit_abs":0.05181,"exit_reason":"trailing_stop_loss","initial_stop_loss_abs":6.524,"initial_stop_loss_ratio":-0.1,"stop_loss_abs":7.304,"stop_loss_ratio":-0.005,"min_rate":7.244,"max_rate":7.34,"is_open":false,"enter_tag":"buy_signal_3","leverage":1.0,"is_short":false,"open_timestamp":1681162200000,"close_timestamp":1681164000000,"orders":[{"amount":1.25,"safe_price":7.248,"ft_order_side":"buy","order_filled_timestamp":1681162200000,"ft_is_entry":true},{"amount":1.25,"safe_price":7.304,"ft_order_side":"sell","order_filled_timestamp":1681164000000,"ft_is_entry":false}]},{"pair":"TRX/USDT","stake_amount":9.15656,"max_stake_amount":9.15656,"amount":137.9,"open_date":"2023-04-11 10:05:00+00:00","close_date":"2023-04-11 17:30:00+00:00","open_rate":0.0664,"close_rate":0.06741,"fee_open":0.001,"fee_close":0.001,"trade_duration":445,"profit_ratio":0.013182449970938225,"profit_abs":0.1208266,"exit_reason":"trailing_stop_loss","initial_stop_loss_abs":0.05976,"initial_stop_loss_ratio":-0.1,"stop_loss_abs":0.06741,"stop_loss_ratio":-0.005,"min_rate":0.06533,"max_rate":0.06774000000000001,"is_open":false,"enter_tag":"buy_signal_3","leverage":1.0,"is_short":false,"open_timestamp":1681207500000,"close_timestamp":1681234200000,"orders":[{"amount":137.9,"safe_price":0.0664,"ft_order_side":"buy","order_filled_timestamp":1681207500000,"ft_is_entry":true},{"amount":137.9,"safe_price":0.06741,"ft_order_side":"sell","order_filled_timestamp":1681234200000,"ft_is_entry":false}]},{"pair":"LTC/USDT","stake_amount":9.11424,"max_stake_amount":9.11424,"amount":0.096,"open_date":"2023-04-11 12:20:00+00:00","close_date":"2023-04-14 00:40:00+00:00","open_rate":94.94,"close_rate":96.72,"fee_open":0.001,"fee_close":0.001,"trade_duration":3620,"profit_ratio":0.0167132214741231,"profit_abs":0.15248064,"exit_reason":"trailing_stop_loss","initial_stop_loss_abs":85.45,"initial_stop_loss_ratio":-0.1,"stop_loss_abs":96.72,"stop_loss_ratio":-0.005,"min_rate":90.87,"max_rate":97.2,"is_open":false,"enter_tag":"buy_signal_3","leverage":1.0,"is_short":false,"open_timestamp":1681215600000,"close_timestamp":1681432800000,"orders":[{"amount":0.096,"safe_price":94.94,"ft_order_side":"buy","order_filled_timestamp":1681215600000,"ft_is_entry":true},{"amount":0.096,"safe_price":96.72,"ft_order_side":"sell","order_filled_timestamp":1681432800000,"ft_is_entry":false}]},{"pair":"MATIC/USDT","stake_amount":8.97702,"max_stake_amount":8.97702,"amount":7.8,"open_date":"2023-04-05 11:25:00+00:00","close_date":"2023-04-14 01:10:00+00:00","open_rate":1.1509,"close_rate":1.1642,"fee_open":0.001,"fee_close":0.001,"trade_duration":12345,"profit_ratio":0.00953508217388659,"profit_abs":0.08568222,"exit_reason":"trailing_stop_loss","initial_stop_loss_abs":1.0359,"initial_stop_loss_ratio":-0.1,"stop_loss_abs":1.1642,"stop_loss_ratio":-0.005,"min_rate":1.0809,"max_rate":1.17,"is_open":false,"enter_tag":"buy_signal_3","leverage":1.0,"is_short":false,"open_timestamp":1680693900000,"close_timestamp":1681434600000,"orders":[{"amount":7.8,"safe_price":1.1509,"ft_order_side":"buy","order_filled_timestamp":1680693900000,"ft_is_entry":true},{"amount":7.8,"safe_price":1.1642,"ft_order_side":"sell","order_filled_timestamp":1681434600000,"ft_is_entry":false}]},{"pair":"DOT/USDT","stake_amount":9.24202,"max_stake_amount":9.24202,"amount":1.37,"open_date":"2023-04-14 07:40:00+00:00","close_date":"2023-04-15 17:05:00+00:00","open_rate":6.746,"close_rate":6.815,"fee_open":0.001,"fee_close":0.001,"trade_duration":2005,"profit_ratio":0.008209845298490422,"profit_abs":0.07595143,"exit_reason":"trailing_stop_loss","initial_stop_loss_abs":6.072,"initial_stop_loss_ratio":-0.1,"stop_loss_abs":6.815,"stop_loss_ratio":-0.005,"min_rate":6.535,"max_rate":6.849,"is_open":false,"enter_tag":"buy_signal_3","leverage":1.0,"is_short":false,"open_timestamp":1681458000000,"close_timestamp":1681578300000,"orders":[{"amount":1.37,"safe_price":6.746,"ft_order_side":"buy","order_filled_timestamp":1681458000000,"ft_is_entry":true},{"amount":1.37,"safe_price":6.815,"ft_order_side":"sell","order_filled_timestamp":1681578300000,"ft_is_entry":false}]},{"pair":"SOL/USDT","stake_amount":9.2167,"max_stake_amount":9.2167,"amount":0.37,"open_date":"2023-04-14 10:55:00+00:00","close_date":"2023-04-16 20:40:00+00:00","open_rate":24.91,"close_rate":25.12,"fee_open":0.001,"fee_close":0.001,"trade_duration":3465,"profit_ratio":0.006415503404664384,"profit_abs":0.0591889,"exit_reason":"trailing_stop_loss","initial_stop_loss_abs":22.42,"initial_stop_loss_ratio":-0.1,"stop_loss_abs":25.12,"stop_loss_ratio":-0.005,"min_rate":23.73,"max_rate":25.24,"is_open":false,"enter_tag":"buy_signal_3","leverage":1.0,"is_short":false,"open_timestamp":1681469700000,"close_timestamp":1681677600000,"orders":[{"amount":0.37,"safe_price":24.91,"ft_order_side":"buy","order_filled_timestamp":1681469700000,"ft_is_entry":true},{"amount":0.37,"safe_price":25.12,"ft_order_side":"sell","order_filled_timestamp":1681677600000,"ft_is_entry":false}]},{"pair":"XRP/USDT","stake_amount":8.8281,"max_stake_amount":8.8281,"amount":17.0,"open_date":"2023-04-15 17:25:00+00:00","close_date":"2023-04-18 12:15:00+00:00","open_rate":0.5193,"close_rate":0.5238,"fee_open":0.001,"fee_close":0.001,"trade_duration":4010,"profit_ratio":0.006650195558341139,"profit_abs":0.0587673,"exit_reason":"trailing_stop_loss","initial_stop_loss_abs":0.4674,"initial_stop_loss_ratio":-0.1,"stop_loss_abs":0.5238,"stop_loss_ratio":-0.005,"min_rate":0.5066,"max_rate":0.5264,"is_open":false,"enter_tag":"buy_signal_3","leverage":1.0,"is_short":false,"open_timestamp":1681579500000,"close_timestamp":1681820100000,"orders":[{"amount":17.0,"safe_price":0.5193,"ft_order_side":"buy","order_filled_timestamp":1681579500000,"ft_is_entry":true},{"amount":17.0,"safe_price":0.5238,"ft_order_side":"sell","order_filled_timestamp":1681820100000,"ft_is_entry":false}]},{"pair":"AVAX/USDT","stake_amount":9.2224,"max_stake_amount":9.2224,"amount":0.44,"open_date":"2023-04-18 17:45:00+00:00","close_date":"2023-04-19 00:20:00+00:00","open_rate":20.96,"close_rate":21.13,"fee_open":0.001,"fee_close":0.001,"trade_duration":395,"profit_ratio":0.006096479856021841,"profit_abs":0.0562804,"exit_reason":"trailing_stop_loss","initial_stop_loss_abs":18.87,"initial_stop_loss_ratio":-0.1,"stop_loss_abs":21.13,"stop_loss_ratio":-0.005,"min_rate":20.88,"max_rate":21.23,"is_open":false,"enter_tag":"buy_signal_3","leverage":1.0,"is_short":false,"open_timestamp":1681839900000,"close_timestamp":1681863600000,"orders":[{"amount":0.44,"safe_price":20.96,"ft_order_side":"buy","order_filled_timestamp":1681839900000,"ft_is_entry":true},{"amount":0.44,"safe_price":21.13,"ft_order_side":"sell","order_filled_timestamp":1681863600000,"ft_is_entry":false}]},{"pair":"AVAX/USDT","stake_amount":9.2796,"max_stake_amount":9.2796,"amount":0.44,"open_date":"2023-04-19 03:25:00+00:00","close_date":"2023-04-19 08:20:00+00:00","open_rate":21.09,"close_rate":18.99,"fee_open":0.001,"fee_close":0.001,"trade_duration":295,"profit_ratio":-0.10137231189862769,"profit_abs":-0.9416352,"exit_reason":"stop_loss","initial_stop_loss_abs":18.99,"initial_stop_loss_ratio":-0.1,"stop_loss_abs":18.99,"stop_loss_ratio":-0.1,"min_rate":18.7,"max_rate":21.11,"is_open":false,"enter_tag":"buy_signal_1","leverage":1.0,"is_short":false,"open_timestamp":1681874700000,"close_timestamp":1681892400000,"orders":[{"amount":0.44,"safe_price":21.09,"ft_order_side":"buy","order_filled_timestamp":1681874700000,"ft_is_entry":true},{"amount":0.44,"safe_price":18.99,"ft_order_side":"sell","order_filled_timestamp":1681892400000,"ft_is_entry":false}]},{"pair":"XRP/USDT","stake_amount":8.2943,"max_stake_amount":8.2943,"amount":17.0,"open_date":"2023-04-19 08:25:00+00:00","close_date":"2023-04-19 08:25:00+00:00","open_rate":0.4879,"close_rate":0.49033950000000004,"fee_open":0.001,"fee_close":0.001,"trade_duration":0,"profit_ratio":0.002992008172674413,"profit_abs":0.02484143,"exit_reason":"trailing_stop_loss","initial_stop_loss_abs":0.4392,"initial_stop_loss_ratio":-0.1,"stop_loss_abs":0.4969,"stop_loss_ratio":-0.005,"min_rate":0.4873,"max_rate":0.4993,"is_open":false,"enter_tag":"buy_signal_3","leverage":1.0,"is_short":false,"open_timestamp":1681892700000,"close_timestamp":1681892700000,"orders":[{"amount":17.0,"safe_price":0.4879,"ft_order_side":"buy","order_filled_timestamp":1681892700000,"ft_is_entry":true},{"amount":17.0,"safe_price":0.49033950000000004,"ft_order_side":"sell","order_filled_timestamp":1681892700000,"ft_is_entry":false}]},{"pair":"DOT/USDT","stake_amount":8.64166,"max_stake_amount":8.64166,"amount":1.34,"open_date":"2023-04-19 12:05:00+00:00","close_date":"2023-04-19 14:15:00+00:00","open_rate":6.449,"close_rate":6.508,"fee_open":0.001,"fee_close":0.001,"trade_duration":130,"profit_ratio":0.007132424096294464,"profit_abs":0.06169762,"exit_reason":"trailing_stop_loss","initial_stop_loss_abs":5.805,"initial_stop_loss_ratio":-0.1,"stop_loss_abs":6.508,"stop_loss_ratio":-0.005,"min_rate":6.445,"max_rate":6.54,"is_open":false,"enter_tag":"buy_signal_3","leverage":1.0,"is_short":false,"open_timestamp":1681905900000,"close_timestamp":1681913700000,"orders":[{"amount":1.34,"safe_price":6.449,"ft_order_side":"buy","order_filled_timestamp":1681905900000,"ft_is_entry":true},{"amount":1.34,"safe_price":6.508,"ft_order_side":"sell","order_filled_timestamp":1681913700000,"ft_is_entry":false}]},{"pair":"ADA/USDT","stake_amount":9.29223,"max_stake_amount":9.29223,"amount":20.7,"open_date":"2023-04-17 00:10:00+00:00","close_date":"2023-04-20 16:00:00+00:00","open_rate":0.4489,"close_rate":0.4041,"fee_open":0.001,"fee_close":0.001,"trade_duration":5270,"profit_ratio":-0.10159811229091693,"profit_abs":-0.9450171,"exit_reason":"stop_loss","initial_stop_loss_abs":0.4041,"initial_stop_loss_ratio":-0.1,"stop_loss_abs":0.4041,"stop_loss_ratio":-0.1,"min_rate":0.3947,"max_rate":0.44980000000000003,"is_open":false,"enter_tag":"buy_signal_3","leverage":1.0,"is_short":false,"open_timestamp":1681690200000,"close_timestamp":1682006400000,"orders":[{"amount":20.7,"safe_price":0.4489,"ft_order_side":"buy","order_filled_timestamp":1681690200000,"ft_is_entry":true},{"amount":20.7,"safe_price":0.4041,"ft_order_side":"sell","order_filled_timestamp":1682006400000,"ft_is_entry":false}]},{"pair":"ADA/USDT","stake_amount":8.6086,"max_stake_amount":8.6086,"amount":21.5,"open_date":"2023-04-20 16:05:00+00:00","close_date":"2023-04-20 16:35:00+00:00","open_rate":0.40040000000000003,"close_rate":0.4034,"fee_open":0.001,"fee_close":0.001,"trade_duration":30,"profit_ratio":0.0054795354495654185,"profit_abs":0.0472183,"exit_reason":"trailing_stop_loss","initial_stop_loss_abs":0.3604,"initial_stop_loss_ratio":-0.1,"stop_loss_abs":0.4034,"stop_loss_ratio":-0.005,"min_rate":0.4,"max_rate":0.40540000000000004,"is_open":false,"enter_tag":"buy_signal_3","leverage":1.0,"is_short":false,"open_timestamp":1682006700000,"close_timestamp":1682008500000,"orders":[{"amount":21.5,"safe_price":0.40040000000000003,"ft_order_side":"buy","order_filled_timestamp":1682006700000,"ft_is_entry":true},{"amount":21.5,"safe_price":0.4034,"ft_order_side":"sell","order_filled_timestamp":1682008500000,"ft_is_entry":false}]},{"pair":"SOL/USDT","stake_amount":8.648,"max_stake_amount":8.648,"amount":0.4,"open_date":"2023-04-20 19:25:00+00:00","close_date":"2023-04-20 19:45:00+00:00","open_rate":21.62,"close_rate":21.78,"fee_open":0.001,"fee_close":0.001,"trade_duration":20,"profit_ratio":0.005387766719866627,"profit_abs":0.04664,"exit_reason":"trailing_stop_loss","initial_stop_loss_abs":19.46,"initial_stop_loss_ratio":-0.1,"stop_loss_abs":21.78,"stop_loss_ratio":-0.005,"min_rate":21.59,"max_rate":21.88,"is_open":false,"enter_tag":"buy_signal_3","leverage":1.0,"is_short":false,"open_timestamp":1682018700000,"close_timestamp":1682019900000,"orders":[{"amount":0.4,"safe_price":21.62,"ft_order_side":"buy","order_filled_timestamp":1682018700000,"ft_is_entry":true},{"amount":0.4,"safe_price":21.78,"ft_order_side":"sell","order_filled_timestamp":1682019900000,"ft_is_entry":false}]},{"pair":"ADA/USDT","stake_amount":8.69736,"max_stake_amount":8.69736,"amount":21.7,"open_date":"2023-04-20 20:05:00+00:00","close_date":"2023-04-21 06:15:00+00:00","open_rate":0.40080000000000005,"close_rate":0.4047,"fee_open":0.001,"fee_close":0.001,"trade_duration":610,"profit_ratio":0.007713095287945587,"profit_abs":0.06715065,"exit_reason":"trailing_stop_loss","initial_stop_loss_abs":0.3608,"initial_stop_loss_ratio":-0.1,"stop_loss_abs":0.4047,"stop_loss_ratio":-0.005,"min_rate":0.39880000000000004,"max_rate":0.4067,"is_open":false,"enter_tag":"buy_signal_3","leverage":1.0,"is_short":false,"open_timestamp":1682021100000,"close_timestamp":1682057700000,"orders":[{"amount":21.7,"safe_price":0.40080000000000005,"ft_order_side":"buy","order_filled_timestamp":1682021100000,"ft_is_entry":true},{"amount":21.7,"safe_price":0.4047,"ft_order_side":"sell","order_filled_timestamp":1682057700000,"ft_is_entry":false}]},{"pair":"BTC/USDT","stake_amount":8.4698879,"max_stake_amount":8.4698879,"amount":0.00029,"open_date":"2023-04-19 17:20:00+00:00","close_date":"2023-04-26 12:25:00+00:00","open_rate":29206.51,"close_rate":29651.0,"fee_open":0.001,"fee_close":0.001,"trade_duration":9785,"profit_ratio":0.013190457727509982,"profit_abs":0.11183342,"exit_reason":"trailing_stop_loss","initial_stop_loss_abs":26285.86,"initial_stop_loss_ratio":-0.1,"stop_loss_abs":29651.0,"stop_loss_ratio":-0.005,"min_rate":26942.82,"max_rate":29800.0,"is_open":false,"enter_tag":"buy_signal_3","leverage":1.0,"is_short":false,"open_timestamp":1681924800000,"close_timestamp":1682511900000,"orders":[{"amount":0.00029,"safe_price":29206.51,"ft_order_side":"buy","order_filled_timestamp":1681924800000,"ft_is_entry":true},{"amount":0.00029,"safe_price":29651.0,"ft_order_side":"sell","order_filled_timestamp":1682511900000,"ft_is_entry":false}]},{"pair":"MATIC/USDT","stake_amount":8.76876,"max_stake_amount":8.76876,"amount":8.4,"open_date":"2023-04-21 06:35:00+00:00","close_date":"2023-04-26 12:30:00+00:00","open_rate":1.0439,"close_rate":1.052,"fee_open":0.001,"fee_close":0.001,"trade_duration":7555,"profit_ratio":0.005745858701122615,"profit_abs":0.05043444,"exit_reason":"trailing_stop_loss","initial_stop_loss_abs":0.9396,"initial_stop_loss_ratio":-0.1,"stop_loss_abs":1.052,"stop_loss_ratio":-0.005,"min_rate":0.9495,"max_rate":1.0572,"is_open":false,"enter_tag":"buy_signal_3","leverage":1.0,"is_short":false,"open_timestamp":1682058900000,"close_timestamp":1682512200000,"orders":[{"amount":8.4,"safe_price":1.0439,"ft_order_side":"buy","order_filled_timestamp":1682058900000,"ft_is_entry":true},{"amount":8.4,"safe_price":1.052,"ft_order_side":"sell","order_filled_timestamp":1682512200000,"ft_is_entry":false}]},{"pair":"ADA/USDT","stake_amount":8.85384,"max_stake_amount":8.85384,"amount":21.6,"open_date":"2023-04-26 19:10:00+00:00","close_date":"2023-04-27 15:20:00+00:00","open_rate":0.40990000000000004,"close_rate":0.4135,"fee_open":0.001,"fee_close":0.001,"trade_duration":1210,"profit_ratio":0.006767080199624723,"profit_abs":0.05997456,"exit_reason":"trailing_stop_loss","initial_stop_loss_abs":0.369,"initial_stop_loss_ratio":-0.1,"stop_loss_abs":0.4135,"stop_loss_ratio":-0.005,"min_rate":0.3778,"max_rate":0.41550000000000004,"is_open":false,"enter_tag":"buy_signal_3","leverage":1.0,"is_short":false,"open_timestamp":1682536200000,"close_timestamp":1682608800000,"orders":[{"amount":21.6,"safe_price":0.40990000000000004,"ft_order_side":"buy","order_filled_timestamp":1682536200000,"ft_is_entry":true},{"amount":21.6,"safe_price":0.4135,"ft_order_side":"sell","order_filled_timestamp":1682608800000,"ft_is_entry":false}]},{"pair":"BTC/USDT","stake_amount":8.5106097,"max_stake_amount":8.5106097,"amount":0.00029,"open_date":"2023-04-26 19:20:00+00:00","close_date":"2023-04-27 18:25:00+00:00","open_rate":29346.93,"close_rate":29591.86,"fee_open":0.001,"fee_close":0.001,"trade_duration":1385,"profit_ratio":0.0063313403308304025,"profit_abs":0.05393745,"exit_reason":"trailing_stop_loss","initial_stop_loss_abs":26412.24,"initial_stop_loss_ratio":-0.1,"stop_loss_abs":29591.86,"stop_loss_ratio":-0.005,"min_rate":27235.0,"max_rate":29740.56,"is_open":false,"enter_tag":"buy_signal_3","leverage":1.0,"is_short":false,"open_timestamp":1682536800000,"close_timestamp":1682619900000,"orders":[{"amount":0.00029,"safe_price":29346.93,"ft_order_side":"buy","order_filled_timestamp":1682536800000,"ft_is_entry":true},{"amount":0.00029,"safe_price":29591.86,"ft_order_side":"sell","order_filled_timestamp":1682619900000,"ft_is_entry":false}]},{"pair":"ADA/USDT","stake_amount":8.90235,"max_stake_amount":8.90235,"amount":21.9,"open_date":"2023-04-27 22:55:00+00:00","close_date":"2023-04-28 07:55:00+00:00","open_rate":0.40650000000000003,"close_rate":0.4096,"fee_open":0.001,"fee_close":0.001,"trade_duration":540,"profit_ratio":0.00561283734715469,"profit_abs":0.05001741,"exit_reason":"trailing_stop_loss","initial_stop_loss_abs":0.3659,"initial_stop_loss_ratio":-0.1,"stop_loss_abs":0.4096,"stop_loss_ratio":-0.005,"min_rate":0.40640000000000004,"max_rate":0.4116,"is_open":false,"enter_tag":"buy_signal_3","leverage":1.0,"is_short":false,"open_timestamp":1682636100000,"close_timestamp":1682668500000,"orders":[{"amount":21.9,"safe_price":0.40650000000000003,"ft_order_side":"buy","order_filled_timestamp":1682636100000,"ft_is_entry":true},{"amount":21.9,"safe_price":0.4096,"ft_order_side":"sell","order_filled_timestamp":1682668500000,"ft_is_entry":false}]},{"pair":"DOGE/USDT","stake_amount":8.89998,"max_stake_amount":8.89998,"amount":111.0,"open_date":"2023-04-28 12:25:00+00:00","close_date":"2023-04-29 05:40:00+00:00","open_rate":0.08018,"close_rate":0.0808,"fee_open":0.001,"fee_close":0.001,"trade_duration":1035,"profit_ratio":0.005719149894754784,"profit_abs":0.05095122,"exit_reason":"trailing_stop_loss","initial_stop_loss_abs":0.07217,"initial_stop_loss_ratio":-0.1,"stop_loss_abs":0.0808,"stop_loss_ratio":-0.005,"min_rate":0.07892,"max_rate":0.08120000000000001,"is_open":false,"enter_tag":"buy_signal_1","leverage":1.0,"is_short":false,"open_timestamp":1682684700000,"close_timestamp":1682746800000,"orders":[{"amount":111.0,"safe_price":0.08018,"ft_order_side":"buy","order_filled_timestamp":1682684700000,"ft_is_entry":true},{"amount":111.0,"safe_price":0.0808,"ft_order_side":"sell","order_filled_timestamp":1682746800000,"ft_is_entry":false}]},{"pair":"TRX/USDT","stake_amount":9.19695,"max_stake_amount":9.19695,"amount":138.3,"open_date":"2023-04-11 19:50:00+00:00","close_date":"2023-04-29 07:15:00+00:00","open_rate":0.0665,"close_rate":0.06715,"fee_open":0.001,"fee_close":0.001,"trade_duration":25165,"profit_ratio":0.007756904206270571,"profit_abs":0.0714112,"exit_reason":"trailing_stop_loss","initial_stop_loss_abs":0.05986,"initial_stop_loss_ratio":-0.1,"stop_loss_abs":0.06715,"stop_loss_ratio":-0.005,"min_rate":0.062110000000000005,"max_rate":0.06748000000000001,"is_open":false,"enter_tag":"buy_signal_3","leverage":1.0,"is_short":false,"open_timestamp":1681242600000,"close_timestamp":1682752500000,"orders":[{"amount":138.3,"safe_price":0.0665,"ft_order_side":"buy","order_filled_timestamp":1681242600000,"ft_is_entry":true},{"amount":138.3,"safe_price":0.06715,"ft_order_side":"sell","order_filled_timestamp":1682752500000,"ft_is_entry":false}]},{"pair":"LTC/USDT","stake_amount":8.938,"max_stake_amount":8.938,"amount":0.1,"open_date":"2023-04-29 08:20:00+00:00","close_date":"2023-04-29 13:15:00+00:00","open_rate":89.38,"close_rate":90.75,"fee_open":0.001,"fee_close":0.001,"trade_duration":295,"profit_ratio":0.013299186827940464,"profit_abs":0.118987,"exit_reason":"trailing_stop_loss","initial_stop_loss_abs":80.45,"initial_stop_loss_ratio":-0.1,"stop_loss_abs":90.75,"stop_loss_ratio":-0.005,"min_rate":89.23,"max_rate":91.2,"is_open":false,"enter_tag":"buy_signal_3","leverage":1.0,"is_short":false,"open_timestamp":1682756400000,"close_timestamp":1682774100000,"orders":[{"amount":0.1,"safe_price":89.38,"ft_order_side":"buy","order_filled_timestamp":1682756400000,"ft_is_entry":true},{"amount":0.1,"safe_price":90.75,"ft_order_side":"sell","order_filled_timestamp":1682774100000,"ft_is_entry":false}]},{"pair":"ADA/USDT","stake_amount":8.9355,"max_stake_amount":8.9355,"amount":22.2,"open_date":"2023-04-29 08:20:00+00:00","close_date":"2023-04-29 15:05:00+00:00","open_rate":0.4025,"close_rate":0.4057,"fee_open":0.001,"fee_close":0.001,"trade_duration":405,"profit_ratio":0.005936423824622582,"profit_abs":0.05309796,"exit_reason":"trailing_stop_loss","initial_stop_loss_abs":0.3623,"initial_stop_loss_ratio":-0.1,"stop_loss_abs":0.4057,"stop_loss_ratio":-0.005,"min_rate":0.402,"max_rate":0.4077,"is_open":false,"enter_tag":"buy_signal_3","leverage":1.0,"is_short":false,"open_timestamp":1682756400000,"close_timestamp":1682780700000,"orders":[{"amount":22.2,"safe_price":0.4025,"ft_order_side":"buy","order_filled_timestamp":1682756400000,"ft_is_entry":true},{"amount":22.2,"safe_price":0.4057,"ft_order_side":"sell","order_filled_timestamp":1682780700000,"ft_is_entry":false}]},{"pair":"ETH/USDT","stake_amount":8.903022,"max_stake_amount":8.903022,"amount":0.0047,"open_date":"2023-04-29 17:35:00+00:00","close_date":"2023-04-30 15:00:00+00:00","open_rate":1894.26,"close_rate":1912.94,"fee_open":0.001,"fee_close":0.001,"trade_duration":1285,"profit_ratio":0.007843665630875412,"profit_abs":0.06990216,"exit_reason":"trailing_stop_loss","initial_stop_loss_abs":1704.84,"initial_stop_loss_ratio":-0.1,"stop_loss_abs":1912.94,"stop_loss_ratio":-0.005,"min_rate":1890.61,"max_rate":1922.55,"is_open":false,"enter_tag":"buy_signal_3","leverage":1.0,"is_short":false,"open_timestamp":1682789700000,"close_timestamp":1682866800000,"orders":[{"amount":0.0047,"safe_price":1894.26,"ft_order_side":"buy","order_filled_timestamp":1682789700000,"ft_is_entry":true},{"amount":0.0047,"safe_price":1912.94,"ft_order_side":"sell","order_filled_timestamp":1682866800000,"ft_is_entry":false}]},{"pair":"BTC/USDT","stake_amount":8.5012688,"max_stake_amount":8.5012688,"amount":0.00029,"open_date":"2023-04-27 22:55:00+00:00","close_date":"2023-04-30 15:15:00+00:00","open_rate":29314.72,"close_rate":29716.65,"fee_open":0.001,"fee_close":0.001,"trade_duration":3860,"profit_ratio":0.011685462614858002,"profit_abs":0.0994406,"exit_reason":"trailing_stop_loss","initial_stop_loss_abs":26383.25,"initial_stop_loss_ratio":-0.1,"stop_loss_abs":29716.65,"stop_loss_ratio":-0.005,"min_rate":28891.0,"max_rate":29865.97,"is_open":false,"enter_tag":"buy_signal_3","leverage":1.0,"is_short":false,"open_timestamp":1682636100000,"close_timestamp":1682867700000,"orders":[{"amount":0.00029,"safe_price":29314.72,"ft_order_side":"buy","order_filled_timestamp":1682636100000,"ft_is_entry":true},{"amount":0.00029,"safe_price":29716.65,"ft_order_side":"sell","order_filled_timestamp":1682867700000,"ft_is_entry":false}]},{"pair":"ADA/USDT","stake_amount":9.0048,"max_stake_amount":9.0048,"amount":22.4,"open_date":"2023-04-29 17:35:00+00:00","close_date":"2023-04-30 15:30:00+00:00","open_rate":0.402,"close_rate":0.406,"fee_open":0.001,"fee_close":0.001,"trade_duration":1315,"profit_ratio":0.007932366141321364,"profit_abs":0.0715008,"exit_reason":"trailing_stop_loss","initial_stop_loss_abs":0.3618,"initial_stop_loss_ratio":-0.1,"stop_loss_abs":0.406,"stop_loss_ratio":-0.005,"min_rate":0.39840000000000003,"max_rate":0.40800000000000003,"is_open":false,"enter_tag":"buy_signal_3","leverage":1.0,"is_short":false,"open_timestamp":1682789700000,"close_timestamp":1682868600000,"orders":[{"amount":22.4,"safe_price":0.402,"ft_order_side":"buy","order_filled_timestamp":1682789700000,"ft_is_entry":true},{"amount":22.4,"safe_price":0.406,"ft_order_side":"sell","order_filled_timestamp":1682868600000,"ft_is_entry":false}]},{"pair":"BTC/USDT","stake_amount":8.814243,"max_stake_amount":8.814243,"amount":0.0003,"open_date":"2023-04-30 19:10:00+00:00","close_date":"2023-05-01 20:55:00+00:00","open_rate":29380.81,"close_rate":27773.0,"fee_open":0.001,"fee_close":0.001,"trade_duration":1545,"profit_ratio":-0.056611798636610075,"profit_abs":-0.49948914,"exit_reason":"force_exit","initial_stop_loss_abs":26442.73,"initial_stop_loss_ratio":-0.1,"stop_loss_abs":26442.73,"stop_loss_ratio":-0.1,"min_rate":27666.95,"max_rate":29486.5,"is_open":false,"enter_tag":"buy_signal_3","leverage":1.0,"is_short":false,"open_timestamp":1682881800000,"close_timestamp":1682974500000,"orders":[{"amount":0.0003,"safe_price":29380.81,"ft_order_side":"buy","order_filled_timestamp":1682881800000,"ft_is_entry":true},{"amount":0.0003,"safe_price":27773.0,"ft_order_side":"sell","order_filled_timestamp":1682974500000,"ft_is_entry":false}]},{"pair":"ETH/USDT","stake_amount":8.970232,"max_stake_amount":8.970232,"amount":0.0047,"open_date":"2023-04-30 19:10:00+00:00","close_date":"2023-05-01 20:55:00+00:00","open_rate":1908.56,"close_rate":1814.31,"fee_open":0.001,"fee_close":0.001,"trade_duration":1545,"profit_ratio":-0.051282115950008596,"profit_abs":-0.46047249,"exit_reason":"force_exit","initial_stop_loss_abs":1717.71,"initial_stop_loss_ratio":-0.1,"stop_loss_abs":1717.71,"stop_loss_ratio":-0.1,"min_rate":1807.15,"max_rate":1911.97,"is_open":false,"enter_tag":"buy_signal_3","leverage":1.0,"is_short":false,"open_timestamp":1682881800000,"close_timestamp":1682974500000,"orders":[{"amount":0.0047,"safe_price":1908.56,"ft_order_side":"buy","order_filled_timestamp":1682881800000,"ft_is_entry":true},{"amount":0.0047,"safe_price":1814.31,"ft_order_side":"sell","order_filled_timestamp":1682974500000,"ft_is_entry":false}]},{"pair":"DOGE/USDT","stake_amount":9.08859,"max_stake_amount":9.08859,"amount":113.0,"open_date":"2023-04-30 19:10:00+00:00","close_date":"2023-05-01 20:55:00+00:00","open_rate":0.08043,"close_rate":0.07807,"fee_open":0.001,"fee_close":0.001,"trade_duration":1545,"profit_ratio":-0.03128166127047142,"profit_abs":-0.2845905,"exit_reason":"force_exit","initial_stop_loss_abs":0.07239,"initial_stop_loss_ratio":-0.1,"stop_loss_abs":0.07239,"stop_loss_ratio":-0.1,"min_rate":0.07733000000000001,"max_rate":0.08054,"is_open":false,"enter_tag":"buy_signal_3","leverage":1.0,"is_short":false,"open_timestamp":1682881800000,"close_timestamp":1682974500000,"orders":[{"amount":113.0,"safe_price":0.08043,"ft_order_side":"buy","order_filled_timestamp":1682881800000,"ft_is_entry":true},{"amount":113.0,"safe_price":0.07807,"ft_order_side":"sell","order_filled_timestamp":1682974500000,"ft_is_entry":false}]}],"locks":[],"best_pair":{"key":"DOGE/USDT","trades":8,"profit_mean":0.005248259279611785,"profit_mean_pct":0.5248259279611786,"profit_sum":0.04198607423689428,"profit_sum_pct":4.2,"profit_total_abs":0.35258896,"profit_total":0.0141035584,"profit_total_pct":1.41,"duration_avg":"19:18:00","wins":7,"draws":0,"losses":1},"worst_pair":{"key":"AVAX/USDT","trades":2,"profit_mean":-0.04763791602130293,"profit_mean_pct":-4.763791602130293,"profit_sum":-0.09527583204260585,"profit_sum_pct":-9.53,"profit_total_abs":-0.8853548,"profit_total":-0.035414192,"profit_total_pct":-3.54,"duration_avg":"5:45:00","wins":1,"draws":0,"losses":1},"results_per_pair":[{"key":"DOGE/USDT","trades":8,"profit_mean":0.005248259279611785,"profit_mean_pct":0.5248259279611786,"profit_sum":0.04198607423689428,"profit_sum_pct":4.2,"profit_total_abs":0.35258896,"profit_total":0.0141035584,"profit_total_pct":1.41,"duration_avg":"19:18:00","wins":7,"draws":0,"losses":1},{"key":"SOL/USDT","trades":6,"profit_mean":0.006742260759450175,"profit_mean_pct":0.6742260759450175,"profit_sum":0.04045356455670105,"profit_sum_pct":4.05,"profit_total_abs":0.3441061,"profit_total":0.013764244000000002,"profit_total_pct":1.38,"duration_avg":"11:04:00","wins":6,"draws":0,"losses":0},{"key":"TRX/USDT","trades":4,"profit_mean":0.00929739659122561,"profit_mean_pct":0.929739659122561,"profit_sum":0.03718958636490244,"profit_sum_pct":3.72,"profit_total_abs":0.3396214,"profit_total":0.013584856000000001,"profit_total_pct":1.36,"duration_avg":"5 days, 23:15:00","wins":4,"draws":0,"losses":0},{"key":"LTC/USDT","trades":3,"profit_mean":0.012174918199315148,"profit_mean_pct":1.2174918199315148,"profit_sum":0.03652475459794544,"profit_sum_pct":3.65,"profit_total_abs":0.3293068,"profit_total":0.013172272,"profit_total_pct":1.32,"duration_avg":"21:52:00","wins":3,"draws":0,"losses":0},{"key":"ETH/USDT","trades":11,"profit_mean":0.00347227596190339,"profit_mean_pct":0.347227596190339,"profit_sum":0.038195035580937294,"profit_sum_pct":3.82,"profit_total_abs":0.3067823700000001,"profit_total":0.012271294800000004,"profit_total_pct":1.23,"duration_avg":"1 day, 4:04:00","wins":10,"draws":0,"losses":1},{"key":"XRP/USDT","trades":4,"profit_mean":0.005137707787031121,"profit_mean_pct":0.513770778703112,"profit_sum":0.020550831148124483,"profit_sum_pct":2.06,"profit_total_abs":0.18099953,"profit_total":0.0072399812,"profit_total_pct":0.72,"duration_avg":"20:34:00","wins":4,"draws":0,"losses":0},{"key":"BTC/USDT","trades":9,"profit_mean":0.0022348957180111434,"profit_mean_pct":0.22348957180111434,"profit_sum":0.02011406146210029,"profit_sum_pct":2.01,"profit_total_abs":0.15083783000000006,"profit_total":0.006033513200000003,"profit_total_pct":0.6,"duration_avg":"3 days, 4:02:00","wins":8,"draws":0,"losses":1},{"key":"DOT/USDT","trades":2,"profit_mean":0.007671134697392443,"profit_mean_pct":0.7671134697392443,"profit_sum":0.015342269394784886,"profit_sum_pct":1.53,"profit_total_abs":0.13764905,"profit_total":0.005505962,"profit_total_pct":0.55,"duration_avg":"17:48:00","wins":2,"draws":0,"losses":0},{"key":"MATIC/USDT","trades":2,"profit_mean":0.007640470437504602,"profit_mean_pct":0.7640470437504602,"profit_sum":0.015280940875009204,"profit_sum_pct":1.53,"profit_total_abs":0.13611666,"profit_total":0.0054446664,"profit_total_pct":0.54,"duration_avg":"6 days, 21:50:00","wins":2,"draws":0,"losses":0},{"key":"LINK/USDT","trades":1,"profit_mean":0.005712830216141474,"profit_mean_pct":0.5712830216141473,"profit_sum":0.005712830216141474,"profit_sum_pct":0.57,"profit_total_abs":0.05181,"profit_total":0.0020724000000000003,"profit_total_pct":0.21,"duration_avg":"0:30:00","wins":1,"draws":0,"losses":0},{"key":"ATOM/USDT","trades":0,"profit_mean":0.0,"profit_mean_pct":0.0,"profit_sum":0.0,"profit_sum_pct":0.0,"profit_total_abs":0.0,"profit_total":0.0,"profit_total_pct":0.0,"duration_avg":"0:00","wins":0,"draws":0,"losses":0},{"key":"ADA/USDT","trades":14,"profit_mean":-0.00032531804473597713,"profit_mean_pct":-0.032531804473597714,"profit_sum":-0.0045544526263036796,"profit_sum_pct":-0.46,"profit_total_abs":-0.10622974000000004,"profit_total":-0.0042491896000000015,"profit_total_pct":-0.42,"duration_avg":"1 day, 3:28:00","wins":13,"draws":0,"losses":1},{"key":"AVAX/USDT","trades":2,"profit_mean":-0.04763791602130293,"profit_mean_pct":-4.763791602130293,"profit_sum":-0.09527583204260585,"profit_sum_pct":-9.53,"profit_total_abs":-0.8853548,"profit_total":-0.035414192,"profit_total_pct":-3.54,"duration_avg":"5:45:00","wins":1,"draws":0,"losses":1},{"key":"TOTAL","trades":66,"profit_mean":0.0025987827843125958,"profit_mean_pct":0.2598782784312596,"profit_sum":0.17151966376463132,"profit_sum_pct":17.15,"profit_total_abs":1.3382341600000005,"profit_total":0.05352936640000002,"profit_total_pct":5.35,"duration_avg":"1 day, 16:53:00","wins":61,"draws":0,"losses":5}],"results_per_enter_tag":[{"key":"buy_signal_3","trades":61,"profit_mean":0.003985274442892643,"profit_mean_pct":0.39852744428926434,"profit_sum":0.24310174101645124,"profit_sum_pct":24.31,"profit_total_abs":2.0225192299999994,"profit_total":0.08090076919999997,"profit_total_pct":8.09,"duration_avg":"1 day, 17:13:00","wins":57,"draws":0,"losses":4},{"key":"buy_signal_1","trades":5,"profit_mean":-0.01431641545036399,"profit_mean_pct":-1.431641545036399,"profit_sum":-0.07158207725181995,"profit_sum_pct":-7.16,"profit_total_abs":-0.68428507,"profit_total":-0.027371402800000003,"profit_total_pct":-2.74,"duration_avg":"1 day, 12:50:00","wins":4,"draws":0,"losses":1},{"key":"TOTAL","trades":66,"profit_mean":0.0025987827843125958,"profit_mean_pct":0.2598782784312596,"profit_sum":0.17151966376463132,"profit_sum_pct":17.15,"profit_total_abs":1.3382341600000005,"profit_total":0.05352936640000002,"profit_total_pct":5.35,"duration_avg":"1 day, 16:53:00","wins":61,"draws":0,"losses":5}],"exit_reason_summary":[{"exit_reason":"trailing_stop_loss","trades":61,"wins":61,"draws":0,"losses":0,"profit_mean":0.008420748587069935,"profit_mean_pct":0.84,"profit_sum":0.513665663811266,"profit_sum_pct":51.37,"profit_total_abs":4.469438589999999,"profit_total":0.17122188793708867,"profit_total_pct":17.12},{"exit_reason":"force_exit","trades":3,"wins":0,"draws":0,"losses":3,"profit_mean":-0.04639185861903003,"profit_mean_pct":-4.64,"profit_sum":-0.1391755758570901,"profit_sum_pct":-13.92,"profit_total_abs":-1.24455213,"profit_total":-0.04639185861903003,"profit_total_pct":-4.64},{"exit_reason":"stop_loss","trades":2,"wins":0,"draws":0,"losses":2,"profit_mean":-0.10148521209477232,"profit_mean_pct":-10.15,"profit_sum":-0.20297042418954464,"profit_sum_pct":-20.3,"profit_total_abs":-1.8866523000000002,"profit_total":-0.06765680806318154,"profit_total_pct":-6.77}],"left_open_trades":[{"key":"DOGE/USDT","trades":1,"profit_mean":-0.03128166127047142,"profit_mean_pct":-3.128166127047142,"profit_sum":-0.03128166127047142,"profit_sum_pct":-3.13,"profit_total_abs":-0.2845905,"profit_total":-0.01138362,"profit_total_pct":-1.14,"duration_avg":"1 day, 1:45:00","wins":0,"draws":0,"losses":1},{"key":"ETH/USDT","trades":1,"profit_mean":-0.051282115950008596,"profit_mean_pct":-5.1282115950008595,"profit_sum":-0.051282115950008596,"profit_sum_pct":-5.13,"profit_total_abs":-0.46047249,"profit_total":-0.0184188996,"profit_total_pct":-1.84,"duration_avg":"1 day, 1:45:00","wins":0,"draws":0,"losses":1},{"key":"BTC/USDT","trades":1,"profit_mean":-0.056611798636610075,"profit_mean_pct":-5.661179863661007,"profit_sum":-0.056611798636610075,"profit_sum_pct":-5.66,"profit_total_abs":-0.49948914,"profit_total":-0.0199795656,"profit_total_pct":-2.0,"duration_avg":"1 day, 1:45:00","wins":0,"draws":0,"losses":1},{"key":"TOTAL","trades":3,"profit_mean":-0.04639185861903003,"profit_mean_pct":-4.639185861903003,"profit_sum":-0.1391755758570901,"profit_sum_pct":-13.92,"profit_total_abs":-1.24455213,"profit_total":-0.0497820852,"profit_total_pct":-4.98,"duration_avg":"1 day, 1:45:00","wins":0,"draws":0,"losses":3}],"total_trades":66,"trade_count_long":66,"trade_count_short":0,"total_volume":575.3127324,"avg_stake_amount":8.71685958181818,"profit_mean":0.0025987827843125958,"profit_median":0.006717103676846425,"profit_total":0.05352936640000002,"profit_total_long":0.05352936640000002,"profit_total_short":0.0,"profit_total_abs":1.3382341600000005,"profit_total_long_abs":1.3382341600000005,"profit_total_short_abs":0.0,"cagr":0.541218525451171,"expectancy":0.032377756874077734,"sortino":2.161422303655678,"sharpe":2.874771000713918,"calmar":32.5972503693045,"profit_factor":1.4273863907378284,"backtest_start":"2023-03-18 14:15:00","backtest_start_ts":1679148900000,"backtest_end":"2023-05-01 20:55:00","backtest_end_ts":1682974500000,"backtest_days":44,"backtest_run_start_ts":1682975047,"backtest_run_end_ts":1682975050,"trades_per_day":1.5,"market_change":-0.004115547475058453,"pairlist":["ADA/USDT","BTC/USDT","ETH/USDT","XRP/USDT","DOGE/USDT","MATIC/USDT","SOL/USDT","DOT/USDT","LTC/USDT","TRX/USDT","AVAX/USDT","LINK/USDT","ATOM/USDT"],"stake_amount":"unlimited","stake_currency":"USDT","stake_currency_decimals":3,"starting_balance":25,"dry_run_wallet":25,"final_balance":26.33823416,"rejected_signals":73569,"timedout_entry_orders":0,"timedout_exit_orders":0,"canceled_trade_entries":0,"canceled_entry_orders":0,"replaced_entry_orders":0,"max_open_trades":3,"max_open_trades_setting":3,"timeframe":"5m","timeframe_detail":"","timerange":"","enable_protections":false,"strategy_name":"Saturn5","stoploss":-0.1,"trailing_stop":true,"trailing_stop_positive":0.005,"trailing_stop_positive_offset":0.01,"trailing_only_offset_is_reached":true,"use_custom_stoploss":false,"minimal_roi":{"0":10},"use_exit_signal":false,"exit_profit_only":false,"exit_profit_offset":0.0,"ignore_roi_if_entry_signal":false,"backtest_best_day":0.0403272656266599,"backtest_worst_day":-0.1391755758570901,"backtest_best_day_abs":0.33409201,"backtest_worst_day_abs":-1.24455213,"winning_days":26,"draw_days":16,"losing_days":3,"daily_profit":[["2023-03-18",0.1020312],["2023-03-19",0.13356897],["2023-03-20",0.05280565],["2023-03-21",0.33409201],["2023-03-22",0.31346212],["2023-03-23",0.11627315],["2023-03-24",0.0],["2023-03-25",0.0],["2023-03-26",0.0],["2023-03-27",0.0],["2023-03-28",0.0],["2023-03-29",0.20206473],["2023-03-30",0.17265692],["2023-03-31",0.17605385],["2023-04-01",0.11774066],["2023-04-02",0.064698],["2023-04-03",0.30589765],["2023-04-04",0.30473395],["2023-04-05",0.12359525],["2023-04-06",0.0],["2023-04-07",0.0],["2023-04-08",0.0],["2023-04-09",0.0],["2023-04-10",0.23155077],["2023-04-11",0.1208266],["2023-04-12",0.0],["2023-04-13",0.0],["2023-04-14",0.23816286],["2023-04-15",0.07595143],["2023-04-16",0.0591889],["2023-04-17",0.0],["2023-04-18",0.0587673],["2023-04-19",-0.79881575],["2023-04-20",-0.8511588],["2023-04-21",0.06715065],["2023-04-22",0.0],["2023-04-23",0.0],["2023-04-24",0.0],["2023-04-25",0.0],["2023-04-26",0.16226786],["2023-04-27",0.11391201],["2023-04-28",0.05001741],["2023-04-29",0.29444738],["2023-04-30",0.24084356],["2023-05-01",-1.24455213]],"wins":61,"losses":5,"draws":0,"holding_avg":"1 day, 16:53:00","holding_avg_s":147180.0,"winner_holding_avg":"1 day, 17:27:00","winner_holding_avg_s":149220.0,"loser_holding_avg":"1 day, 10:00:00","loser_holding_avg_s":122400.0,"max_drawdown":0.21562043687340263,"max_drawdown_account":0.07130252186192802,"max_relative_drawdown":0.07130252186192802,"max_drawdown_abs":2.0221682100000002,"drawdown_start":"2023-04-19 00:20:00","drawdown_start_ts":1681863600000.0,"drawdown_end":"2023-05-01 20:55:00","drawdown_end_ts":1682974500000.0,"max_drawdown_low":1.3382341599999996,"max_drawdown_high":3.3604023699999996,"csum_min":25.1020312,"csum_max":28.36040237}},"strategy_comparison":[{"key":"Saturn5","trades":66,"profit_mean":0.0025987827843125958,"profit_mean_pct":0.2598782784312596,"profit_sum":0.17151966376463132,"profit_sum_pct":17.15,"profit_total_abs":1.3382341600000005,"profit_total":0.05352936640000002,"profit_total_pct":5.35,"duration_avg":"1 day, 16:53:00","wins":61,"draws":0,"losses":5,"max_drawdown_account":0.07130252186192802,"max_drawdown_abs":"2.022"}]}